pypi_to_sqlite/__init__.py
pypi_to_sqlite/cli.py
pypi_to_sqlite-0.2.3.dist-info/LICENSE
pypi_to_sqlite-0.2.3.dist-info/METADATA
pypi_to_sqlite-0.2.3.dist-info/WHEEL
pypi_to_sqlite-0.2.3.dist-info/entry_points.txt
pypi_to_sqlite-0.2.3.dist-info/top_level.txt
pypi_to_sqlite-0.2.3.dist-info/RECORD
