Metadata-Version: 2.1
Name: pypi-to-sqlite
Version: 0.2.3
Summary: Load data about Python packages from PyPI into SQLite
Home-page: https://github.com/simonw/pypi-to-sqlite
Author: Simon Willison
License: Apache License, Version 2.0
Project-URL: Issues, https://github.com/simonw/pypi-to-sqlite/issues
Project-URL: CI, https://github.com/simonw/pypi-to-sqlite/actions
Project-URL: Changelog, https://github.com/simonw/pypi-to-sqlite/releases
Requires-Python: >=3.7
License-File: LICENSE
Requires-Dist: click
Requires-Dist: sqlite-utils
Requires-Dist: httpx
Provides-Extra: test
Requires-Dist: pytest ; extra == 'test'
Requires-Dist: pytest-httpx ; extra == 'test'
Requires-Dist: cogapp ; extra == 'test'
